Metadata-Version: 1.1
Name: subprocess.run
Version: 0.0.4
Summary: The subprocess module extension to run processes.
Home-page: https://github.com/xando/subprocess.run
Author: Sebastian Pawluś
Author-email: sebastian.pawlus@gmail.com
License: Copyright (c) 2013, Sebastian Pawluś.
